{
    "loser": "another",
    "pick": [
        {
            "time": "2017-12-06T02:42:32+0000",
            "type": "HeroSelect",
            "payload": {
                "Player": "bb1e1924-7696-11e4-bfe8-06d90c28bf1a",
                "Hero": "*Celeste*",
                "Team": "1",
                "Handle": "Neothetruth"
            }
        },
        {
            "time": "2017-12-06T02:42:34+0000",
            "type": "HeroSelect",
            "payload": {
                "Player": "9e014626-749d-11e5-b01b-06b48b82cd49",
                "Hero": "*Fortress*",
                "Team": "2",
                "Handle": "GODZLYFE"
            }
        },
        {
            "time": "2017-12-06T02:42:52+0000",
            "type": "HeroSelect",
            "payload": {
                "Player": "a50cdebc-1962-11e5-9203-06d90c28bf1a",
                "Hero": "*Blackfeather*",
                "Team": "1",
                "Handle": "cubodeath"
            }
        },
        {
            "time": "2017-12-06T02:42:55+0000",
            "type": "HeroSelect",
            "payload": {
                "Player": "9e155cb6-9345-11e6-a377-06f4ee369f53",
                "Hero": "*Lyra*",
                "Team": "1",
                "Handle": "Alfort79"
            }
        },
        {
            "time": "2017-12-06T02:43:12+0000",
            "type": "HeroSelect",
            "payload": {
                "Player": "da4d9d6e-13c2-11e5-bc72-06d90c28bf1a",
                "Hero": "*Vox*",
                "Team": "2",
                "Handle": "drackleonn"
            }
        },
        {
            "time": "2017-12-06T02:43:36+0000",
            "type": "HeroSelect",
            "payload": {
                "Player": "b8903a1a-7651-11e4-8854-06d90c28bf1a",
                "Hero": "*Grace*",
                "Team": "2",
                "Handle": "Varkias"
            }
        }
    ],
    "winner": "left/blue"
}