{
    "loser": "another",
    "pick": [
        {
            "time": "2017-12-06T04:39:03+0000",
            "type": "HeroSelect",
            "payload": {
                "Player": "b22bdaae-6f83-11e5-887e-0628b69bf6d1",
                "Hero": "*Varya*",
                "Team": "2",
                "Handle": "TitaniumFury"
            }
        },
        {
            "time": "2017-12-06T04:39:03+0000",
            "type": "HeroSelect",
            "payload": {
                "Player": "7ae05f46-a5fa-11e4-800e-06eb725f8a76",
                "Hero": "*Vox*",
                "Team": "2",
                "Handle": "xORPHEUSx"
            }
        },
        {
            "time": "2017-12-06T04:39:25+0000",
            "type": "HeroSelect",
            "payload": {
                "Player": "0b113bb0-1699-11e7-8a86-0223dbc2587a",
                "Hero": "*Lyra*",
                "Team": "2",
                "Handle": "emmaskyeward"
            }
        },
        {
            "time": "2017-12-06T04:39:48+0000",
            "type": "HeroSelect",
            "payload": {
                "Player": "427e8b80-b424-11e5-bfb8-06eb725f8a76",
                "Hero": "*Catherine*",
                "Team": "1",
                "Handle": "SmirknTwerk"
            }
        },
        {
            "time": "2017-12-06T04:39:51+0000",
            "type": "HeroSelect",
            "payload": {
                "Player": "c93d329a-9b30-11e6-a71f-067e8bc536fd",
                "Hero": "*Varya*",
                "Team": "1",
                "Handle": "Fear0Law"
            }
        },
        {
            "time": "2017-12-06T04:40:00+0000",
            "type": "HeroSelect",
            "payload": {
                "Player": "36b97c44-a6de-11e6-96b1-06a9175d25fa",
                "Hero": "*Glaive*",
                "Team": "1",
                "Handle": "Goljee"
            }
        }
    ],
    "winner": "left/blue"
}