{
    "loser": "left/blue",
    "pick": [
        {
            "time": "2017-12-06T00:08:54+0000",
            "type": "HeroSelect",
            "payload": {
                "Player": "50391d04-9af5-11e6-9d28-06f4ee369f53",
                "Hero": "*Catherine*",
                "Team": "1",
                "Handle": "Xenor12"
            }
        },
        {
            "time": "2017-12-06T00:08:55+0000",
            "type": "HeroSelect",
            "payload": {
                "Player": "68acb396-88e5-11e5-8483-068789513eb5",
                "Hero": "*Kestrel*",
                "Team": "1",
                "Handle": "Nguyenth4"
            }
        },
        {
            "time": "2017-12-06T00:08:56+0000",
            "type": "HeroSelect",
            "payload": {
                "Player": "e8add57a-d827-11e5-a495-06c5ee41a4a5",
                "Hero": "*Krul*",
                "Team": "1",
                "Handle": "CyRUs"
            }
        },
        {
            "time": "2017-12-06T00:09:15+0000",
            "type": "HeroSelect",
            "payload": {
                "Player": "4a1b053a-bebb-11e4-b92c-06eb725f8a76",
                "Hero": "*Ardan*",
                "Team": "2",
                "Handle": "000Storm"
            }
        },
        {
            "time": "2017-12-06T00:09:18+0000",
            "type": "HeroSelect",
            "payload": {
                "Player": "37434984-6ac5-11e5-9d15-06eb725f8a76",
                "Hero": "*Skye*",
                "Team": "2",
                "Handle": "nani7"
            }
        },
        {
            "time": "2017-12-06T00:09:18+0000",
            "type": "HeroSelect",
            "payload": {
                "Player": "f6a80468-f467-11e6-840e-029cb633549e",
                "Hero": "*Koshka*",
                "Team": "2",
                "Handle": "collettte"
            }
        }
    ],
    "winner": "another"
}