{
    "loser": "left/blue",
    "pick": [
        {
            "time": "2017-12-06T03:07:54+0000",
            "type": "HeroBan",
            "payload": {
                "Hero": "*Varya*",
                "Team": "1"
            }
        },
        {
            "time": "2017-12-06T03:08:22+0000",
            "type": "HeroBan",
            "payload": {
                "Hero": "*SAW*",
                "Team": "2"
            }
        },
        {
            "time": "2017-12-06T03:08:32+0000",
            "type": "HeroSelect",
            "payload": {
                "Player": "f45a658e-6f3a-11e4-b86a-06641bcbf424",
                "Hero": "*Baron*",
                "Team": "1",
                "Handle": "Chona7"
            }
        },
        {
            "time": "2017-12-06T03:08:36+0000",
            "type": "HeroSelect",
            "payload": {
                "Player": "83cd4884-4fc7-11e7-8813-06c5ee41a4a5",
                "Hero": "*Koshka*",
                "Team": "2",
                "Handle": "FlipDatTableYEET"
            }
        },
        {
            "time": "2017-12-06T03:08:42+0000",
            "type": "HeroSelect",
            "payload": {
                "Player": "af92e1c8-58fe-11e7-9478-02081e0fc90e",
                "Hero": "*Rona*",
                "Team": "2",
                "Handle": "Mogwai43"
            }
        },
        {
            "time": "2017-12-06T03:08:51+0000",
            "type": "HeroSelect",
            "payload": {
                "Player": "e1717688-6f3f-11e4-bfea-06641bcbf424",
                "Hero": "*Ringo*",
                "Team": "1",
                "Handle": "Bgizzle89"
            }
        },
        {
            "time": "2017-12-06T03:08:59+0000",
            "type": "HeroSelect",
            "payload": {
                "Player": "e2e9df3c-8272-11e4-821c-06eb725f8a76",
                "Hero": "*Reza*",
                "Team": "1",
                "Handle": "Guest94690392"
            }
        },
        {
            "time": "2017-12-06T03:09:05+0000",
            "type": "HeroSelect",
            "payload": {
                "Player": "b073511a-5aeb-11e7-ad2c-020355b21670",
                "Hero": "*Ardan*",
                "Team": "2",
                "Handle": "HoneyBadger3"
            }
        }
    ],
    "winner": "another"
}