{
    "loser": "another",
    "pick": [
        {
            "type": "HeroSelect",
            "time": "2017-12-06T05:17:09+0000",
            "payload": {
                "Player": "867eff44-6583-11e5-8cd5-068789513eb5",
                "Hero": "*Alpha*",
                "Team": "2",
                "Handle": "0buh0"
            }
        },
        {
            "type": "HeroSelect",
            "time": "2017-12-06T05:17:11+0000",
            "payload": {
                "Player": "3fd25ad6-7de5-11e4-a0b9-06eb725f8a76",
                "Hero": "*Koshka*",
                "Team": "2",
                "Handle": "Jjoker0110"
            }
        },
        {
            "type": "HeroSelect",
            "time": "2017-12-06T05:17:11+0000",
            "payload": {
                "Player": "730177f0-2395-11e6-96bb-06388a2f2ea7",
                "Hero": "*Koshka*",
                "Team": "1",
                "Handle": "summeralarm14"
            }
        },
        {
            "type": "HeroSelect",
            "time": "2017-12-06T05:17:12+0000",
            "payload": {
                "Player": "ffd86ee0-6fcd-11e4-9304-062d0b175276",
                "Hero": "*Krul*",
                "Team": "1",
                "Handle": "zabb"
            }
        },
        {
            "type": "HeroSelect",
            "time": "2017-12-06T05:17:30+0000",
            "payload": {
                "Player": "f4b774e2-d59d-11e6-a471-06b48b82cd49",
                "Hero": "*Ardan*",
                "Team": "1",
                "Handle": "RaGhOsT"
            }
        },
        {
            "type": "HeroSelect",
            "time": "2017-12-06T05:17:38+0000",
            "payload": {
                "Player": "25db5322-9c0f-11e6-a9b4-06f4ee369f53",
                "Hero": "*Lyra*",
                "Team": "2",
                "Handle": "taytayob13"
            }
        }
    ],
    "winner": "left/blue"
}