{
    "loser": "another",
    "pick": [
        {
            "time": "2017-12-06T04:34:39+0000",
            "type": "HeroSelect",
            "payload": {
                "Player": "36e6f13a-01ce-11e5-8702-06d90c28bf1a",
                "Hero": "*Joule*",
                "Team": "1",
                "Handle": "Boobookeyz"
            }
        },
        {
            "time": "2017-12-06T04:34:41+0000",
            "type": "HeroSelect",
            "payload": {
                "Player": "e72f8952-95b1-11e7-91c8-06ab1a16f8e5",
                "Hero": "*Grace*",
                "Team": "1",
                "Handle": "ViveX"
            }
        },
        {
            "time": "2017-12-06T04:34:42+0000",
            "type": "HeroSelect",
            "payload": {
                "Player": "b05ed6fe-9245-11e7-9d01-067e8bc536fd",
                "Hero": "*Skaarf*",
                "Team": "1",
                "Handle": "Lebatron"
            }
        },
        {
            "time": "2017-12-06T04:34:49+0000",
            "type": "HeroSelect",
            "payload": {
                "Player": "1970e376-06ce-11e6-8767-06d90c28bf1a",
                "Hero": "*Varya*",
                "Team": "2",
                "Handle": "CrucialReign"
            }
        },
        {
            "time": "2017-12-06T04:35:24+0000",
            "type": "HeroSelect",
            "payload": {
                "Player": "15969f10-b43a-11e6-9aaa-06c5ee41a4a5",
                "Hero": "*Flicker*",
                "Team": "2",
                "Handle": "chosen1pr"
            }
        },
        {
            "time": "2017-12-06T04:35:29+0000",
            "type": "HeroSelect",
            "payload": {
                "Player": "8ca11a86-c525-11e5-825b-0628b69bf6d1",
                "Hero": "*Glaive*",
                "Team": "2",
                "Handle": "jhay02"
            }
        }
    ],
    "winner": "left/blue"
}