{
    "loser": "another",
    "pick": [
        {
            "time": "2017-12-06T03:30:32+0000",
            "type": "HeroBan",
            "payload": {
                "Hero": "*Lyra*",
                "Team": "1"
            }
        },
        {
            "time": "2017-12-06T03:30:48+0000",
            "type": "HeroBan",
            "payload": {
                "Hero": "*Catherine*",
                "Team": "2"
            }
        },
        {
            "time": "2017-12-06T03:31:09+0000",
            "type": "HeroSelect",
            "payload": {
                "Player": "ebb36af0-219d-11e5-97f8-06d90c28bf1a",
                "Hero": "*Ardan*",
                "Team": "1",
                "Handle": "Hallucinated"
            }
        },
        {
            "time": "2017-12-06T03:31:11+0000",
            "type": "HeroSelect",
            "payload": {
                "Player": "5921ebc8-cb08-11e7-8016-02ce883f709a",
                "Hero": "*Varya*",
                "Team": "2",
                "Handle": "RedKes"
            }
        },
        {
            "time": "2017-12-06T03:31:20+0000",
            "type": "HeroSelect",
            "payload": {
                "Player": "45283a9a-79da-11e5-b9da-068789513eb5",
                "Hero": "*Lance*",
                "Team": "2",
                "Handle": "Eddie12314"
            }
        },
        {
            "time": "2017-12-06T03:31:38+0000",
            "type": "HeroSelect",
            "payload": {
                "Player": "2d019caa-a789-11e4-8aab-06d90c28bf1a",
                "Hero": "*Vox*",
                "Team": "1",
                "Handle": "BrokenEyez"
            }
        },
        {
            "time": "2017-12-06T03:31:43+0000",
            "type": "HeroSelect",
            "payload": {
                "Player": "6e02d764-6949-11e5-b30a-06eb725f8a76",
                "Hero": "*Taka*",
                "Team": "1",
                "Handle": "rawrShocka"
            }
        },
        {
            "time": "2017-12-06T03:32:02+0000",
            "type": "HeroSelect",
            "payload": {
                "Player": "fd68beca-34e4-11e6-84ee-06ab1a16f8e5",
                "Hero": "*Glaive*",
                "Team": "2",
                "Handle": "Feeha"
            }
        }
    ],
    "winner": "left/blue"
}