{
    "pick": [
        {
            "time": "2017-12-05T20:28:48+0000",
            "payload": {
                "Hero": "*Catherine*",
                "Team": "1"
            },
            "type": "HeroBan"
        },
        {
            "time": "2017-12-05T20:28:55+0000",
            "payload": {
                "Hero": "*SAW*",
                "Team": "2"
            },
            "type": "HeroBan"
        },
        {
            "time": "2017-12-05T20:28:57+0000",
            "payload": {
                "Player": "593662f8-8b08-11e4-888b-06d90c28bf1a",
                "Handle": "ViirusT",
                "Hero": "*Vox*",
                "Team": "1"
            },
            "type": "HeroSelect"
        },
        {
            "time": "2017-12-05T20:29:12+0000",
            "payload": {
                "Player": "4afe986c-dc39-11e5-8b2f-06eb725f8a76",
                "Handle": "Pichachu",
                "Hero": "*Lyra*",
                "Team": "2"
            },
            "type": "HeroSelect"
        },
        {
            "time": "2017-12-05T20:29:13+0000",
            "payload": {
                "Player": "07c0a09a-664e-11e7-85db-06ab1a16f8e5",
                "Handle": "HonorForTheCarry",
                "Hero": "*Baron*",
                "Team": "2"
            },
            "type": "HeroSelect"
        },
        {
            "time": "2017-12-05T20:29:15+0000",
            "payload": {
                "Player": "b3efa63c-d3af-11e5-9b75-06c5ee41a4a5",
                "Handle": "ItsKamina",
                "Hero": "*Fortress*",
                "Team": "1"
            },
            "type": "HeroSelect"
        },
        {
            "time": "2017-12-05T20:29:18+0000",
            "payload": {
                "Player": "8d6f0e46-e103-11e6-9dcd-06ab1a16f8e5",
                "Handle": "kietg",
                "Hero": "*Lance*",
                "Team": "1"
            },
            "type": "HeroSelect"
        },
        {
            "time": "2017-12-05T20:29:39+0000",
            "payload": {
                "Player": "7bf22aa2-7bbd-11e4-affb-06eb725f8a76",
                "Handle": "Gary",
                "Hero": "*Reim*",
                "Team": "2"
            },
            "type": "HeroSelect"
        }
    ],
    "winner": "another",
    "loser": "left/blue"
}