{
    "loser": "left/blue",
    "pick": [
        {
            "time": "2017-12-06T03:52:28+0000",
            "type": "HeroSelect",
            "payload": {
                "Player": "1bd324c6-d88c-11e7-b325-02ce883f709a",
                "Hero": "*Varya*",
                "Team": "1",
                "Handle": "benziboy2808"
            }
        },
        {
            "time": "2017-12-06T03:52:29+0000",
            "type": "HeroSelect",
            "payload": {
                "Player": "9027eb3a-8e56-11e6-9dfb-068789513eb5",
                "Hero": "*Fortress*",
                "Team": "1",
                "Handle": "EmilianHayashi"
            }
        },
        {
            "time": "2017-12-06T03:52:31+0000",
            "type": "HeroSelect",
            "payload": {
                "Player": "b54a69f6-b731-11e7-b95e-06d90c28bf1a",
                "Hero": "*Krul*",
                "Team": "1",
                "Handle": "KillerHug"
            }
        },
        {
            "time": "2017-12-06T03:52:36+0000",
            "type": "HeroSelect",
            "payload": {
                "Player": "4c02feaa-4223-11e7-b461-06eb725f8a76",
                "Hero": "*Fortress*",
                "Team": "2",
                "Handle": "Quasar321"
            }
        },
        {
            "time": "2017-12-06T03:52:37+0000",
            "type": "HeroSelect",
            "payload": {
                "Player": "d8dad73e-91ac-11e7-8d10-0297ea8a7ddc",
                "Hero": "*Rona*",
                "Team": "2",
                "Handle": "WormWood14"
            }
        },
        {
            "time": "2017-12-06T03:52:49+0000",
            "type": "HeroSelect",
            "payload": {
                "Player": "66e3936e-85e3-11e4-9ad5-06eb725f8a76",
                "Hero": "*Gwen*",
                "Team": "2",
                "Handle": "LtDanger"
            }
        }
    ],
    "winner": "another"
}