{
    "loser": "another",
    "pick": [
        {
            "type": "HeroBan",
            "time": "2017-12-06T04:50:02+0000",
            "payload": {
                "Hero": "*Reim*",
                "Team": "1"
            }
        },
        {
            "type": "HeroBan",
            "time": "2017-12-06T04:50:19+0000",
            "payload": {
                "Hero": "*Lance*",
                "Team": "2"
            }
        },
        {
            "type": "HeroSelect",
            "time": "2017-12-06T04:50:22+0000",
            "payload": {
                "Player": "512e36dc-8958-11e4-a8d3-06d90c28bf1a",
                "Hero": "*Varya*",
                "Team": "1",
                "Handle": "HaKiii"
            }
        },
        {
            "type": "HeroSelect",
            "time": "2017-12-06T04:50:42+0000",
            "payload": {
                "Player": "b4ad4fe6-c89d-11e6-a128-068789513eb5",
                "Hero": "*Samuel*",
                "Team": "2",
                "Handle": "kdaddy1328"
            }
        },
        {
            "type": "HeroSelect",
            "time": "2017-12-06T04:50:57+0000",
            "payload": {
                "Player": "bd25f416-c713-11e5-87c9-06d90c28bf1a",
                "Hero": "*Alpha*",
                "Team": "2",
                "Handle": "FARNSWORTH12"
            }
        },
        {
            "type": "HeroSelect",
            "time": "2017-12-06T04:51:17+0000",
            "payload": {
                "Player": "93959476-0be6-11e7-9383-020ecf4900d0",
                "Hero": "*Phinn*",
                "Team": "1",
                "Handle": "Eee333"
            }
        },
        {
            "type": "HeroSelect",
            "time": "2017-12-06T04:51:37+0000",
            "payload": {
                "Player": "dcce426c-3f7e-11e6-807d-06ab1a16f8e5",
                "Hero": "*Kestrel*",
                "Team": "1",
                "Handle": "DerangedParadox"
            }
        },
        {
            "type": "HeroSelect",
            "time": "2017-12-06T04:51:39+0000",
            "payload": {
                "Player": "a9b46e02-9767-11e5-9616-0628b69bf6d1",
                "Hero": "*Glaive*",
                "Team": "2",
                "Handle": "SphinxEquinox"
            }
        }
    ],
    "winner": "left/blue"
}