{
    "pick": [
        {
            "time": "2017-11-05T19:46:44+0000",
            "type": "HeroBan",
            "payload": {
                "Team": "1",
                "Hero": "*Reim*"
            }
        },
        {
            "time": "2017-11-05T19:47:01+0000",
            "type": "HeroBan",
            "payload": {
                "Team": "2",
                "Hero": "*SAW*"
            }
        },
        {
            "time": "2017-11-05T19:47:06+0000",
            "type": "HeroSelect",
            "payload": {
                "Team": "1",
                "Handle": "DoomKing6000",
                "Player": "81e846d4-b407-11e5-ba90-0628b69bf6d1",
                "Hero": "*Blackfeather*"
            }
        },
        {
            "time": "2017-11-05T19:47:24+0000",
            "type": "HeroSelect",
            "payload": {
                "Team": "2",
                "Handle": "Phinnegan",
                "Player": "b9cd2316-cd2a-11e6-b3e3-06eb725f8a76",
                "Hero": "*Glaive*"
            }
        },
        {
            "time": "2017-11-05T19:47:46+0000",
            "type": "HeroSelect",
            "payload": {
                "Team": "2",
                "Handle": "siris108",
                "Player": "7e695766-b159-11e4-a9af-06eb725f8a76",
                "Hero": "*Reza*"
            }
        },
        {
            "time": "2017-11-05T19:48:11+0000",
            "type": "HeroSelect",
            "payload": {
                "Team": "1",
                "Handle": "BoOzKa",
                "Player": "eaedd930-8b28-11e5-a923-06f4ee369f53",
                "Hero": "*Celeste*"
            }
        },
        {
            "time": "2017-11-05T19:48:15+0000",
            "type": "HeroSelect",
            "payload": {
                "Team": "1",
                "Handle": "ohgeekevin",
                "Player": "b6e7b3c6-05b4-11e5-99b2-06eb725f8a76",
                "Hero": "*Flicker*"
            }
        },
        {
            "time": "2017-11-05T19:48:24+0000",
            "type": "HeroSelect",
            "payload": {
                "Team": "2",
                "Handle": "JimbooVC",
                "Player": "a5cb3e94-6919-11e7-b102-02866102f5a6",
                "Hero": "*Ardan*"
            }
        }
    ],
    "winner": "left/blue",
    "loser": "another"
}