{
    "pick": [
        {
            "time": "2017-11-05T16:33:42+0000",
            "type": "HeroSelect",
            "payload": {
                "Team": "1",
                "Handle": "mrnick0626",
                "Player": "99188798-b049-11e7-8f36-06ab1a16f8e5",
                "Hero": "*Catherine*"
            }
        },
        {
            "time": "2017-11-05T16:33:44+0000",
            "type": "HeroSelect",
            "payload": {
                "Team": "2",
                "Handle": "banks2025",
                "Player": "3ab4c34c-8bf7-11e5-a949-068789513eb5",
                "Hero": "*SAW*"
            }
        },
        {
            "time": "2017-11-05T16:33:59+0000",
            "type": "HeroSelect",
            "payload": {
                "Team": "2",
                "Handle": "diego100",
                "Player": "f7a39fe2-4a06-11e5-94c6-068789513eb5",
                "Hero": "*Reim*"
            }
        },
        {
            "time": "2017-11-05T16:34:02+0000",
            "type": "HeroSelect",
            "payload": {
                "Team": "1",
                "Handle": "Twist3dArm0r",
                "Player": "ce6dc918-14f3-11e7-a48a-0297ea8a7ddc",
                "Hero": "*SAW*"
            }
        },
        {
            "time": "2017-11-05T16:34:20+0000",
            "type": "HeroSelect",
            "payload": {
                "Team": "1",
                "Handle": "tanhammer",
                "Player": "fd330466-6577-11e5-bc54-068789513eb5",
                "Hero": "*Reim*"
            }
        },
        {
            "time": "2017-11-05T16:34:25+0000",
            "type": "HeroSelect",
            "payload": {
                "Team": "2",
                "Handle": "DocHum",
                "Player": "2def243a-70c6-11e7-b7fa-06c5ee41a4a5",
                "Hero": "*Flicker*"
            }
        }
    ],
    "winner": "another",
    "loser": "left/blue"
}