{
    "pick": [
        {
            "time": "2017-11-05T19:05:29+0000",
            "type": "HeroSelect",
            "payload": {
                "Team": "1",
                "Handle": "getluckygabe",
                "Player": "3791e620-90c5-11e7-9fdc-06eb725f8a76",
                "Hero": "*Blackfeather*"
            }
        },
        {
            "time": "2017-11-05T19:05:31+0000",
            "type": "HeroSelect",
            "payload": {
                "Team": "2",
                "Handle": "Rastaism7347",
                "Player": "57383988-681c-11e7-b354-068789513eb5",
                "Hero": "*Fortress*"
            }
        },
        {
            "time": "2017-11-05T19:05:44+0000",
            "type": "HeroSelect",
            "payload": {
                "Team": "2",
                "Handle": "jscheffer",
                "Player": "9a43940c-cfa6-11e6-b193-062cb73cdbb1",
                "Hero": "*Skaarf*"
            }
        },
        {
            "time": "2017-11-05T19:05:49+0000",
            "type": "HeroSelect",
            "payload": {
                "Team": "2",
                "Handle": "RAINdropDropTop",
                "Player": "228879f6-cc4e-11e6-81d9-06fc87f1dd11",
                "Hero": "*Krul*"
            }
        },
        {
            "time": "2017-11-05T19:05:54+0000",
            "type": "HeroSelect",
            "payload": {
                "Team": "1",
                "Handle": "XXL3DGENDXX",
                "Player": "ecb519ae-b12d-11e7-84eb-02a5820c0f16",
                "Hero": "*Glaive*"
            }
        },
        {
            "time": "2017-11-05T19:06:02+0000",
            "type": "HeroSelect",
            "payload": {
                "Team": "1",
                "Handle": "BladeCrazed",
                "Player": "88d3be7c-c223-11e5-a5d3-06f4ee369f53",
                "Hero": "*Fortress*"
            }
        }
    ],
    "winner": "left/blue",
    "loser": "another"
}