{
    "pick": [
        {
            "time": "2017-11-05T16:07:29+0000",
            "type": "HeroSelect",
            "payload": {
                "Team": "2",
                "Handle": "ANOLPEES7337",
                "Player": "2b809416-c484-11e6-a9d3-06b48b82cd49",
                "Hero": "*Gwen*"
            }
        },
        {
            "time": "2017-11-05T16:07:53+0000",
            "type": "HeroSelect",
            "payload": {
                "Team": "2",
                "Handle": "DaPhatYo",
                "Player": "9515131e-3335-11e7-b9d7-0263a81144c0",
                "Hero": "*Lyra*"
            }
        },
        {
            "time": "2017-11-05T16:07:54+0000",
            "type": "HeroSelect",
            "payload": {
                "Team": "2",
                "Handle": "TheShyNoob",
                "Player": "3916922c-6d6e-11e7-aee1-0224e22aef46",
                "Hero": "*Blackfeather*"
            }
        },
        {
            "time": "2017-11-05T16:08:10+0000",
            "type": "HeroSelect",
            "payload": {
                "Team": "1",
                "Handle": "FerBlood03",
                "Player": "905e3d46-a67d-11e5-a81a-06eb725f8a76",
                "Hero": "*Vox*"
            }
        },
        {
            "time": "2017-11-05T16:08:13+0000",
            "type": "HeroSelect",
            "payload": {
                "Team": "1",
                "Handle": "KingCobraYt",
                "Player": "47d8b20e-d46c-11e6-aa85-06f4ee369f53",
                "Hero": "*Ardan*"
            }
        },
        {
            "time": "2017-11-05T16:08:15+0000",
            "type": "HeroSelect",
            "payload": {
                "Team": "1",
                "Handle": "bonokoot",
                "Player": "f9aed6ea-6f86-11e4-b4af-06641bcbf424",
                "Hero": "*Reim*"
            }
        }
    ],
    "winner": "another",
    "loser": "left/blue"
}