{
    "pick": [
        {
            "time": "2017-11-05T09:27:07+0000",
            "type": "HeroSelect",
            "payload": {
                "Team": "1",
                "Handle": "nirro123",
                "Player": "ed26eac4-7b83-11e6-859b-06eb725f8a76",
                "Hero": "*Celeste*"
            }
        },
        {
            "time": "2017-11-05T09:27:15+0000",
            "type": "HeroSelect",
            "payload": {
                "Team": "2",
                "Handle": "DeityOfChrist",
                "Player": "cdf5b33e-f366-11e4-8a1c-06eb725f8a76",
                "Hero": "*Blackfeather*"
            }
        },
        {
            "time": "2017-11-05T09:27:27+0000",
            "type": "HeroSelect",
            "payload": {
                "Team": "2",
                "Handle": "Raffa",
                "Player": "42c58180-7d15-11e4-8c8b-06eb725f8a76",
                "Hero": "*Celeste*"
            }
        },
        {
            "time": "2017-11-05T09:27:32+0000",
            "type": "HeroSelect",
            "payload": {
                "Team": "2",
                "Handle": "Wokaholic",
                "Player": "224ce008-3ebd-11e7-b4e4-02b3611af5e6",
                "Hero": "*Lyra*"
            }
        },
        {
            "time": "2017-11-05T09:27:32+0000",
            "type": "HeroSelect",
            "payload": {
                "Team": "1",
                "Handle": "NmekaDaGawd",
                "Player": "652a50c4-04d4-11e5-964b-06d90c28bf1a",
                "Hero": "*Rona*"
            }
        },
        {
            "time": "2017-11-05T09:27:35+0000",
            "type": "HeroSelect",
            "payload": {
                "Team": "1",
                "Handle": "FuneralsAreSad",
                "Player": "9ec4103c-55dc-11e5-81c4-0628b69bf6d1",
                "Hero": "*Ardan*"
            }
        }
    ],
    "winner": "another",
    "loser": "left/blue"
}