{
    "pick": [
        {
            "time": "2017-11-05T13:59:23+0000",
            "type": "HeroSelect",
            "payload": {
                "Team": "1",
                "Handle": "FairyForestKing",
                "Player": "aee15750-f468-11e6-a252-06f4ee369f53",
                "Hero": "*Flicker*"
            }
        },
        {
            "time": "2017-11-05T13:59:38+0000",
            "type": "HeroSelect",
            "payload": {
                "Team": "1",
                "Handle": "Alexander104",
                "Player": "1e4b88c6-7936-11e6-94e3-06fc87f1dd11",
                "Hero": "*Celeste*"
            }
        },
        {
            "time": "2017-11-05T13:59:41+0000",
            "type": "HeroSelect",
            "payload": {
                "Team": "1",
                "Handle": "1337yankees",
                "Player": "b7d9f37a-8366-11e7-a08f-06f4ee369f53",
                "Hero": "*Reza*"
            }
        },
        {
            "time": "2017-11-05T14:00:10+0000",
            "type": "HeroSelect",
            "payload": {
                "Team": "2",
                "Handle": "TCSJoker",
                "Player": "2dcff00e-0823-11e6-984f-06b48b82cd49",
                "Hero": "*Kestrel*"
            }
        },
        {
            "time": "2017-11-05T14:00:12+0000",
            "type": "HeroSelect",
            "payload": {
                "Team": "2",
                "Handle": "BushidoBrownN",
                "Player": "4394c6a6-9eee-11e5-963a-0628b69bf6d1",
                "Hero": "*Alpha*"
            }
        },
        {
            "time": "2017-11-05T14:00:14+0000",
            "type": "HeroSelect",
            "payload": {
                "Team": "2",
                "Handle": "OxTheGreat1",
                "Player": "bbfa67f0-bb9e-11e5-98f1-068789513eb5",
                "Hero": "*Rona*"
            }
        }
    ],
    "winner": "another",
    "loser": "left/blue"
}