{
    "pick": [
        {
            "time": "2017-11-05T15:25:56+0000",
            "type": "HeroSelect",
            "payload": {
                "Team": "1",
                "Handle": "99percentLuck",
                "Player": "b01975ae-4086-11e5-98f0-06b48b82cd49",
                "Hero": "*SAW*"
            }
        },
        {
            "time": "2017-11-05T15:25:59+0000",
            "type": "HeroSelect",
            "payload": {
                "Team": "2",
                "Handle": "BooBerry",
                "Player": "c3e8a3a8-7033-11e4-be2a-06641bcbf424",
                "Hero": "*Taka*"
            }
        },
        {
            "time": "2017-11-05T15:26:14+0000",
            "type": "HeroSelect",
            "payload": {
                "Team": "2",
                "Handle": "PrinceDastan",
                "Player": "497066ec-1c2c-11e5-a694-06eb725f8a76",
                "Hero": "*SAW*"
            }
        },
        {
            "time": "2017-11-05T15:26:27+0000",
            "type": "HeroSelect",
            "payload": {
                "Team": "1",
                "Handle": "TheExorCist",
                "Player": "473711da-4f69-11e5-807c-0628b69bf6d1",
                "Hero": "*Krul*"
            }
        },
        {
            "time": "2017-11-05T15:26:34+0000",
            "type": "HeroSelect",
            "payload": {
                "Team": "2",
                "Handle": "TACTICAL",
                "Player": "225f6f68-de0e-11e5-a26b-062cb73cdbb1",
                "Hero": "*Krul*"
            }
        },
        {
            "time": "2017-11-05T15:26:39+0000",
            "type": "HeroSelect",
            "payload": {
                "Team": "1",
                "Handle": "Halstead",
                "Player": "6549bcea-017f-11e6-81a1-06eb725f8a76",
                "Hero": "*Phinn*"
            }
        }
    ],
    "winner": "left/blue",
    "loser": "another"
}