{
    "pick": [
        {
            "time": "2017-11-05T11:36:33+0000",
            "type": "HeroSelect",
            "payload": {
                "Team": "1",
                "Handle": "808nanislayah",
                "Player": "3048a1a2-fcf0-11e5-861f-06388a2f2ea7",
                "Hero": "*SAW*"
            }
        },
        {
            "time": "2017-11-05T11:36:53+0000",
            "type": "HeroSelect",
            "payload": {
                "Team": "2",
                "Handle": "QueenBeeeX2",
                "Player": "20dd891e-978b-11e5-912e-06d90c28bf1a",
                "Hero": "*Catherine*"
            }
        },
        {
            "time": "2017-11-05T11:36:54+0000",
            "type": "HeroSelect",
            "payload": {
                "Team": "2",
                "Handle": "RexDoom",
                "Player": "b7b37b52-0869-11e5-bc8e-06eb725f8a76",
                "Hero": "*Krul*"
            }
        },
        {
            "time": "2017-11-05T11:36:54+0000",
            "type": "HeroSelect",
            "payload": {
                "Team": "2",
                "Handle": "Ajstylz",
                "Player": "14fe4086-83ad-11e4-800e-06eb725f8a76",
                "Hero": "*Celeste*"
            }
        },
        {
            "time": "2017-11-05T11:37:22+0000",
            "type": "HeroSelect",
            "payload": {
                "Team": "1",
                "Handle": "xPriestlyx",
                "Player": "cb1871ac-d8b1-11e5-a7f9-06eb725f8a76",
                "Hero": "*Flicker*"
            }
        },
        {
            "time": "2017-11-05T11:37:23+0000",
            "type": "HeroSelect",
            "payload": {
                "Team": "1",
                "Handle": "Nirvana001",
                "Player": "03c72fbe-5c4d-11e7-afb3-067e8bc536fd",
                "Hero": "*Baptiste*"
            }
        }
    ],
    "winner": "left/blue",
    "loser": "another"
}