{
    "pick": [
        {
            "time": "2017-11-05T14:22:06+0000",
            "type": "HeroSelect",
            "payload": {
                "Team": "1",
                "Handle": "Vixin",
                "Player": "00902476-7a92-11e4-959c-06eb725f8a76",
                "Hero": "*Lyra*"
            }
        },
        {
            "time": "2017-11-05T14:22:11+0000",
            "type": "HeroSelect",
            "payload": {
                "Team": "2",
                "Handle": "ChronicMassacre",
                "Player": "061c6dae-75b6-11e4-af77-06d90c28bf1a",
                "Hero": "*Kestrel*"
            }
        },
        {
            "time": "2017-11-05T14:22:27+0000",
            "type": "HeroSelect",
            "payload": {
                "Team": "2",
                "Handle": "DarthKazuma",
                "Player": "b8400a22-f238-11e5-8272-06b48b82cd49",
                "Hero": "*Lance*"
            }
        },
        {
            "time": "2017-11-05T14:22:28+0000",
            "type": "HeroSelect",
            "payload": {
                "Team": "2",
                "Handle": "Nietzsche21",
                "Player": "39a8e106-bdf5-11e5-9fa3-06d90c28bf1a",
                "Hero": "*Reim*"
            }
        },
        {
            "time": "2017-11-05T14:22:44+0000",
            "type": "HeroSelect",
            "payload": {
                "Team": "1",
                "Handle": "Bolivias",
                "Player": "60acb202-ae89-11e6-b272-06b48b82cd49",
                "Hero": "*Taka*"
            }
        },
        {
            "time": "2017-11-05T14:22:54+0000",
            "type": "HeroSelect",
            "payload": {
                "Team": "1",
                "Handle": "godzirakid",
                "Player": "ddbdbfc0-70a1-11e4-a9c4-06641bcbf424",
                "Hero": "*Idris*"
            }
        }
    ],
    "winner": "another",
    "loser": "left/blue"
}