{
    "pick": [
        {
            "time": "2017-11-05T21:53:22+0000",
            "type": "HeroBan",
            "payload": {
                "Team": "1",
                "Hero": "*Reim*"
            }
        },
        {
            "time": "2017-11-05T21:53:32+0000",
            "type": "HeroBan",
            "payload": {
                "Team": "2",
                "Hero": "*Blackfeather*"
            }
        },
        {
            "time": "2017-11-05T21:53:56+0000",
            "type": "HeroSelect",
            "payload": {
                "Team": "1",
                "Handle": "trapcat",
                "Player": "69b059b4-7833-11e4-af77-06d90c28bf1a",
                "Hero": "*Vox*"
            }
        },
        {
            "time": "2017-11-05T21:54:00+0000",
            "type": "HeroSelect",
            "payload": {
                "Team": "2",
                "Handle": "EpiphanY",
                "Player": "048d985e-8228-11e4-b525-06d90c28bf1a",
                "Hero": "*Ardan*"
            }
        },
        {
            "time": "2017-11-05T21:54:08+0000",
            "type": "HeroSelect",
            "payload": {
                "Team": "2",
                "Handle": "JoeMiner4501",
                "Player": "4205fdd8-aef7-11e4-ab01-06d90c28bf1a",
                "Hero": "*Taka*"
            }
        },
        {
            "time": "2017-11-05T21:54:14+0000",
            "type": "HeroSelect",
            "payload": {
                "Team": "1",
                "Handle": "Funnyman695",
                "Player": "0d8333d4-cb74-11e4-8c14-06d90c28bf1a",
                "Hero": "*Reza*"
            }
        },
        {
            "time": "2017-11-05T21:54:21+0000",
            "type": "HeroSelect",
            "payload": {
                "Team": "1",
                "Handle": "Ecoumene",
                "Player": "27de08bc-101f-11e6-ad17-06ab1a16f8e5",
                "Hero": "*Lyra*"
            }
        },
        {
            "time": "2017-11-05T21:54:25+0000",
            "type": "HeroSelect",
            "payload": {
                "Team": "2",
                "Handle": "Kiavash",
                "Player": "a5aaaa18-6eb6-11e4-8776-06641bcbf424",
                "Hero": "*Adagio*"
            }
        }
    ],
    "winner": "another",
    "loser": "left/blue"
}