{
    "pick": [
        {
            "time": "2017-11-05T17:07:15+0000",
            "type": "HeroSelect",
            "payload": {
                "Team": "2",
                "Handle": "Nastyyomama",
                "Player": "4205b47a-9e82-11e4-aadc-06eb725f8a76",
                "Hero": "*Adagio*"
            }
        },
        {
            "time": "2017-11-05T17:07:25+0000",
            "type": "HeroSelect",
            "payload": {
                "Team": "1",
                "Handle": "KensterNguyen",
                "Player": "3d56c7b4-5978-11e5-85c2-068789513eb5",
                "Hero": "*SAW*"
            }
        },
        {
            "time": "2017-11-05T17:07:32+0000",
            "type": "HeroSelect",
            "payload": {
                "Team": "1",
                "Handle": "danielovsky",
                "Player": "ff91fa86-88dd-11e4-9a9d-06d90c28bf1a",
                "Hero": "*Ardan*"
            }
        },
        {
            "time": "2017-11-05T17:07:33+0000",
            "type": "HeroSelect",
            "payload": {
                "Team": "2",
                "Handle": "DefiningFire",
                "Player": "c92a9f2a-8603-11e4-a17f-06eb725f8a76",
                "Hero": "*Lance*"
            }
        },
        {
            "time": "2017-11-05T17:07:37+0000",
            "type": "HeroSelect",
            "payload": {
                "Team": "1",
                "Handle": "llMiToll",
                "Player": "9f0b84da-f9f7-11e4-8dac-06d90c28bf1a",
                "Hero": "*Taka*"
            }
        },
        {
            "time": "2017-11-05T17:07:43+0000",
            "type": "HeroSelect",
            "payload": {
                "Team": "2",
                "Handle": "RulerOfClams",
                "Player": "1523c124-8733-11e4-8283-06eb725f8a76",
                "Hero": "*SAW*"
            }
        }
    ],
    "winner": "another",
    "loser": "left/blue"
}